sqwash/__init__.py
sqwash/functional.py
sqwash/qp_solve.py
sqwash/reducers.py
sqwash-0.1.0.dist-info/LICENSE
sqwash-0.1.0.dist-info/METADATA
sqwash-0.1.0.dist-info/WHEEL
sqwash-0.1.0.dist-info/top_level.txt
sqwash-0.1.0.dist-info/RECORD
