Metadata-Version: 2.1
Name: sqwash
Version: 0.1.0
Summary: Distributionally Robust Learning with the Superquantile
Home-page: https://github.com/krishnap25/sqwash
Author: Krishna Pillutla
Author-email: pillutla@cs.washington.edu
License: UNKNOWN
Project-URL: Bug Tracker, https://github.com/krishnap25/sqwash/issues
Platform: UNKNOWN
Classifier: Programming Language :: Python :: 3
Classifier: License :: OSI Approved :: GNU General Public License v3 (GPLv3)
Classifier: Operating System :: OS Independent
Requires-Python: >=3.6
License-File: LICENSE
Requires-Dist: torch (>=1.7.0)
